{
  "schema_version": "evidence_bundle_manifest.v1",
  "project": "DataPulse",
  "generated_at_utc": "2026-03-12T11:46:47Z",
  "bundle_kind": "draft_export",
  "wired": false,
  "plan_path": "/Users/sunyifei/DataPulse/docs/governance/datapulse-blueprint-plan.json",
  "release_tag": "v0.8.0",
  "release_version": "0.8.0",
  "notes_file": "/Users/sunyifei/DataPulse/RELEASE_NOTES.md",
  "notes_section_found": true,
  "ha_readiness_probed": true,
  "files": [
    "code_landing_status.draft.json",
    "release_readiness_fact.draft.json",
    "ha_delivery_facts.draft.json",
    "ha_delivery_landing.draft.json",
    "ha_recovery_preset.draft.json",
    "project_specific_loop_state.draft.json",
    "release_sidecar.draft.json",
    "evidence_bundle_manifest.draft.json"
  ]
}
